nexus_iq_sdk/__init__.py
nexus_iq_sdk/api/__init__.py
nexus_iq_sdk/api/application_categories_api.py
nexus_iq_sdk/api/applications_api.py
nexus_iq_sdk/api/claim_api.py
nexus_iq_sdk/api/components_api.py
nexus_iq_sdk/api/composite_source_control_api.py
nexus_iq_sdk/api/composite_source_control_config_validator_api.py
nexus_iq_sdk/api/config_api.py
nexus_iq_sdk/api/config_artifactory_connection_api.py
nexus_iq_sdk/api/config_crowd_api.py
nexus_iq_sdk/api/config_jira_api.py
nexus_iq_sdk/api/config_mail_api.py
nexus_iq_sdk/api/config_proxy_server_api.py
nexus_iq_sdk/api/config_reverse_proxy_authentication_api.py
nexus_iq_sdk/api/config_saml_api.py
nexus_iq_sdk/api/config_source_control_api.py
nexus_iq_sdk/api/cyclone_dx_api.py
nexus_iq_sdk/api/data_retention_policies_api.py
nexus_iq_sdk/api/endpoints_api.py
nexus_iq_sdk/api/evaluation_api.py
nexus_iq_sdk/api/firewall_api.py
nexus_iq_sdk/api/labels_api.py
nexus_iq_sdk/api/license_legal_metadata_api.py
nexus_iq_sdk/api/organizations_api.py
nexus_iq_sdk/api/policies_api.py
nexus_iq_sdk/api/policy_violations_api.py
nexus_iq_sdk/api/policy_waiver_api.py
nexus_iq_sdk/api/policy_waivers_api.py
nexus_iq_sdk/api/reports_api.py
nexus_iq_sdk/api/repositories_api.py
nexus_iq_sdk/api/role_memberships_api.py
nexus_iq_sdk/api/roles_api.py
nexus_iq_sdk/api/scan_api.py
nexus_iq_sdk/api/search_api.py
nexus_iq_sdk/api/security_overrides_api.py
nexus_iq_sdk/api/source_control_api.py
nexus_iq_sdk/api/source_control_metrics_api.py
nexus_iq_sdk/api/telemetry_api.py
nexus_iq_sdk/api/user_tokens_api.py
nexus_iq_sdk/api/users_api.py
nexus_iq_sdk/api/vulnerabilities_api.py
nexus_iq_sdk/api_client.py
nexus_iq_sdk/configuration.py
nexus_iq_sdk/models/__init__.py
nexus_iq_sdk/models/action.py
nexus_iq_sdk/models/api_application_base_dto.py
nexus_iq_sdk/models/api_application_category_dto.py
nexus_iq_sdk/models/api_application_dto.py
nexus_iq_sdk/models/api_application_evaluation_commit_dto.py
sonatype_nexus_iq_sdk-0.1.0.dist-info/LICENSE
sonatype_nexus_iq_sdk-0.1.0.dist-info/METADATA
sonatype_nexus_iq_sdk-0.1.0.dist-info/WHEEL
sonatype_nexus_iq_sdk-0.1.0.dist-info/RECORD
